project/textlcd.v
module textlcd(clk,resetn,enable,hour,minute,second,LCD_E,LCD_RS,LCD_RW,LCD_DATA);

input resetn,clk;
input [3:0] enable;
input [7:0] hour,minute,second;//7:4-> 10자리 3:0 -> 1자리
output LCD_E,LCD_RS,LCD_RW;
output [7:0]LCD_DATA;

reg[127:0] line1_data,line2_data;

wire LCD_E;
reg LCD_RS,LCD_RW;
reg [7:0] LCD_DATA;
reg [2:0] state;


parameter   delay          =3'b000, 
            function_set   =3'b001,
            entry_mode     =3'b010,
            disp_onoff     =3'b011,
            line1          =3'b100,  
            line2          =3'b101,
            delay_t        =3'b110,
            clear_disp     =3'b111;

parameter zero=8'b00110000, one=8'b00110001, two=8'b00110010, three=8'b00110011,
         four=8'b00110100, five=8'b00110101 ,six=8'b00110110, seven=8'b00110111,
         eight=8'b00111000, nine=8'b00111001,
         
         A=8'b01000001, B=8'b01000010, C=8'b01000011, D=8'b01000100,
         E=8'b01000101, F=8'b01000110, G=8'b01000111, H=8'b01001000,
         I=8'b01001001, J=8'b01001010, K=8'b01001011, L=8'b01001100,
         M=8'b01001101, N=8'b01001110, O=8'b01001111, P=8'b01010000,
         Q=8'b01010001, R=8'b01010010, S=8'b01010011, T=8'b01010100,
         U=8'b01010101, V=8'b01010110, W=8'b01010111, X=8'b01011000,
         Y=8'b01011001, Z=8'b01011010,

         blank=8'b00100000,
         colon=8'b00111010;

integer CNT;

always @(negedge resetn or posedge clk)
begin
   if(!resetn) state = delay;
   else
   begin   
      case(state)//line1,line2,delay,clear_disk에 500CNT --> 500hz == 1s
         delay:            if(CNT==70)    state = function_set;
         function_set:     if(CNT==30)    state = disp_onoff;
         disp_onoff:       if(CNT==30)    state = entry_mode;
         entry_mode:       if(CNT==30)    state = line1;
         line1:            if(CNT==20)    state = line2;
         line2:            if(CNT==20)    state = delay_t;
         delay_t:          if(CNT==360)   state = clear_disp;
         clear_disp:       if(CNT==100)   state = line1;
         default:                         state = delay;
      endcase
   end
end


always @(negedge resetn or posedge clk)
begin
   if(!resetn) CNT=0;
   else
      begin   
         case(state)
            delay:          if(CNT>=70)CNT=0;
                           else CNT=CNT+1;
            function_set:    if(CNT>=30)CNT=0;
                           else CNT=CNT+1;
            disp_onoff:      if(CNT>=30)CNT=0;
                           else CNT=CNT+1;
            entry_mode:      if(CNT>=30)CNT=0;
                           else CNT=CNT+1;
            line1:         if(CNT>=20)CNT=0;
                           else CNT=CNT+1;
            line2:         if(CNT>=20)CNT=0;
                           else CNT=CNT+1;
            delay_t:         if(CNT>=360)CNT=0;
                           else CNT=CNT+1;
            clear_disp:    if(CNT>=100)CNT=0;
                           else CNT=CNT+1;
            default:         CNT=0;
         endcase
      end
end

always @(negedge resetn or posedge clk) 
begin
   if(!resetn)
   begin
      line1_data={blank,blank,blank,blank,blank,blank,blank,blank,blank,blank,blank,blank,blank,blank,blank,blank};
      line2_data={blank,blank,blank,blank,blank,blank,blank,blank,blank,blank,blank,blank,blank,blank,blank,blank};
   end
   else
   begin
      if(enable==4'b1000) begin
      line1_data={blank,blank,blank,blank,blank,blank,C,L,O,C,K,blank,M,O,D,E};
      line2_data={blank,blank,blank,blank,blank,blank,blank,blank,zero+{4'b0,hour[7:4]},zero+{4'b0,hour[3:0]},colon,zero+{4'b0,minute[7:4]},zero+{4'b0,minute[3:0]},colon,zero+{4'b0,second[7:4]},zero+{4'b0,second[3:0]}};
      end
      else if(enable==4'b0100) begin
      line1_data={blank,blank,blank,blank,blank,blank,blank,S,E,T,blank,C,L,O,C,K};
      line2_data={blank,blank,blank,blank,blank,blank,blank,blank,zero+{4'b0,hour[7:4]},zero+{4'b0,hour[3:0]},colon,zero+{4'b0,minute[7:4]},zero+{4'b0,minute[3:0]},colon,zero+{4'b0,second[7:4]},zero+{4'b0,second[3:0]}};
      end
   end
end


always @(negedge resetn or posedge clk)
begin
   if(!resetn) begin
      LCD_RS=1'b1;
      LCD_RW=1'b1;
      LCD_DATA=8'b00000000;
   end
   else
      begin   
         case(state)
            function_set:    begin
                              LCD_RS=1'b0;
                              LCD_RW=1'b0;
                              LCD_DATA=8'b00111000;
                           end
            disp_onoff:      begin
                              LCD_RS=1'b0;
                              LCD_RW=1'b0;
                              LCD_DATA=8'b00001100;
                           end
            entry_mode:      begin
                              LCD_RS=1'b0;
                              LCD_RW=1'b0;
                              LCD_DATA=8'b00000110;
                           end
            line1:         begin
                              LCD_RW=1'b0;
                              case(CNT)
                                 0:begin
                                    LCD_RS=1'b0;LCD_DATA=8'b10000000;//address
                                 end 
                                 1:begin
                                    LCD_RS=1'b1;LCD_DATA=line1_data[127:120];
                                 end
                                 2:begin
                                    LCD_RS=1'b1;LCD_DATA=line1_data[119:112];
                                 end
                                 3:begin
                                    LCD_RS=1'b1;LCD_DATA=line1_data[111:104];
                                 end
                                 4:begin
                                    LCD_RS=1'b1;LCD_DATA=line1_data[103:96];
                                 end
                                 5:begin
                                    LCD_RS=1'b1;LCD_DATA=line1_data[95:88];
                                 end
                                 6:begin
                                    LCD_RS=1'b1;LCD_DATA=line1_data[87:80];
                                 end
                                 7:begin
                                    LCD_RS=1'b1;LCD_DATA=line1_data[79:72];
                                 end
                                 8:begin
                                    LCD_RS=1'b1;LCD_DATA=line1_data[71:64];
                                 end
                                 9:begin
                                    LCD_RS=1'b1;LCD_DATA=line1_data[63:56];
                                 end
                                 10:begin
                                    LCD_RS=1'b1;LCD_DATA=line1_data[55:48];
                                 end
                                 11:begin
                                    LCD_RS=1'b1;LCD_DATA=line1_data[47:40];
                                 end
                                 12:begin
                                    LCD_RS=1'b1;LCD_DATA=line1_data[39:32];
                                 end
                                 13:begin
                                    LCD_RS=1'b1;LCD_DATA=line1_data[31:24];
                                 end
                                 14:begin
                                    LCD_RS=1'b1;LCD_DATA=line1_data[23:16];
                                 end
                                 15:begin
                                    LCD_RS=1'b1;LCD_DATA=line1_data[15:8];
                                 end
                                 16:begin
                                    LCD_RS=1'b1;LCD_DATA=line1_data[7:0];
                                 end
                                 default:begin
                                    LCD_RS=1'b1;LCD_DATA=8'b00100000;
                                 end
                              endcase
                           end
            line2:         begin
                              LCD_RW=1'b0;
                              case(CNT)
                                 0:begin
                                    LCD_RS=1'b0;LCD_DATA=8'b11000000;//addressx
                                 end
                                 1:begin
                                    LCD_RS=1'b1;LCD_DATA=line2_data[127:120];
                                 end
                                 2:begin
                                    LCD_RS=1'b1;LCD_DATA=line2_data[119:112];
                                 end
                                 3:begin
                                    LCD_RS=1'b1;LCD_DATA=line2_data[111:104];
                                 end
                                 4:begin
                                    LCD_RS=1'b1;LCD_DATA=line2_data[103:96];
                                 end
                                 5:begin
                                    LCD_RS=1'b1;LCD_DATA=line2_data[95:88];
                                 end
                                 6:begin
                                    LCD_RS=1'b1;LCD_DATA=line2_data[87:80];
                                 end
                                 7:begin
                                    LCD_RS=1'b1;LCD_DATA=line2_data[79:72];
                                 end
                                 8:begin
                                    LCD_RS=1'b1;LCD_DATA=line2_data[71:64];
                                 end
                                 9:begin
                                    LCD_RS=1'b1;LCD_DATA=line2_data[63:56];
                                 end
                                 10:begin
                                    LCD_RS=1'b1;LCD_DATA=line2_data[55:48];
                                 end
                                 11:begin
                                    LCD_RS=1'b1;LCD_DATA=line2_data[47:40];
                                 end
                                 12:begin
                                    LCD_RS=1'b1;LCD_DATA=line2_data[39:32];
                                 end
                                 13:begin
                                    LCD_RS=1'b1;LCD_DATA=line2_data[31:24];
                                 end
                                 14:begin
                                    LCD_RS=1'b1;LCD_DATA=line2_data[23:16];
                                 end
                                 15:begin
                                    LCD_RS=1'b1;LCD_DATA=line2_data[15:8];
                                 end
                                 16:begin
                                    LCD_RS=1'b1;LCD_DATA=line2_data[7:0];
                                 end
                                 default:begin
                                    LCD_RS=1'b1;LCD_DATA=8'b00100000;//
                                 end
                              endcase
                           end
            delay_t:         begin
                              LCD_RS=1'b0;
                              LCD_RW=1'b0;
                              LCD_DATA=8'b00000010;
                           end
            clear_disp:    begin
                              LCD_RS=1'b0;
                              LCD_RW=1'b0;
                              LCD_DATA=8'b00000001;
                           end
            default:         begin
                              LCD_RS=1'b1;
                              LCD_RW=1'b1;
                              LCD_DATA=8'b00000000;
                           end
         endcase
      end
end

assign LCD_E=clk;

endmodule

project/register.v
module register(clk, rst, in, en, out);
  input clk, rst, en;
  input [3:0]in;
  output reg [3:0]out;
  
  always@(posedge clk or negedge rst) begin
    if (!rst) begin
      out <= 4'b0;
    end
    else begin
      if (en) out <= in;
    end
  end
endmodule

project/display.v
module display(rst, clk, enable,scan_data, valid, r0,r1,r2,r3,r4,r5, en);
  input rst, clk;
  input [3:0] enable;
  input [11:0]scan_data;
  input valid;
  output reg [3:0]r0,r1,r2,r3,r4,r5;
  output reg en;
  reg [11:0]r8;
  reg [2:0]r9;
  reg [3:0]w;
  
  initial en <= 0;
  
  always@(posedge clk or negedge rst) begin
    if (!rst) begin
      r8 <= 12'b000000000000;
      r9 <= 3'b000;
      en <= 0;
      w <= 0;
      r0 <= 0;
      r1 <= 0;
      r2 <= 0;
      r3 <= 0;
      r4 <= 0;
      r5 <= 0;
    end
    else if(enable==4'b1000)begin
      r8 <= 12'b000000000000;
      r9 <= 3'b000;
      en <= 0;
      w <= 0;
      r0 <= 0;
      r1 <= 0;
      r2 <= 0;
      r3 <= 0;
      r4 <= 0;
      r5 <= 0;
    end
    else begin
      if (valid) begin
        case(scan_data)
        12'b000000000001 : begin r8 <= 12'b000000000001; w <= 1; end //1
        12'b000000000010 : begin r8 <= 12'b000000000010; w <= 2; end //2
        12'b000000000100 : begin r8 <= 12'b000000000100; w <= 3; end //3
        12'b000000001000 : begin r8 <= 12'b000000001000; w <= 4; end //4
        12'b000000010000 : begin r8 <= 12'b000000010000; w <= 5; end //5
        12'b000000100000 : begin r8 <= 12'b000000100000; w <= 6; end //6
        12'b000001000000 : begin r8 <= 12'b000001000000; w <= 7; end //7
        12'b000010000000 : begin r8 <= 12'b000010000000; w <= 8; end //8
        12'b000100000000 : begin r8 <= 12'b000100000000; w <= 9; end //9
        12'b001000000000 : begin r8 <= 12'b001000000000; en <= 1; end         //*
        12'b010000000000 : begin r8 <= 12'b010000000000; w <= 0; end //0
        12'b100000000000 : begin r8 <= 12'b100000000000; r9 <= r9 + 1; w <= 0; end //#
        endcase
      end      
      else begin   
        case(r9)
          3'b000 : r0 <= w;
          3'b001 : r1 <= w;
          3'b010 : r2 <= w;
          3'b011 : r3 <= w;
          3'b100 : r4 <= w;
          3'b101 : r5 <= w;
        endcase
      end
    end
  end
endmodule

project/keypad_scan.v
module keypad_scan(
input rst, clk,
input [3:0] enable,
input [11:0] keypad_in,
output reg [11:0] scan_out = 0,
output reg valid = 0);

reg en;

always @(posedge clk or negedge rst) begin

if (~rst) begin		//active-low reset
	en <= 0;
	scan_out <= 0;
	valid <= 0;
end
else begin
	if (keypad_in && ~en) begin	//if keypad input occurred, generate output and valid signal
		scan_out <= keypad_in;
		valid <= 1'b1;
		en <= 1'b1;
	end
	else if (keypad_in && en) begin	//after 1 clock passed, make valid signel to 0
		valid <= 0;
		scan_out <= 0;
	end
	else begin		//when keypad input disappear, return to initial condition
		en <= 0;
		valid <= 0;
		scan_out <= 0;
	end
end

end

endmodule

project/keypad.v
module keypad(rst, clk, enable,keypad_in, h,m,s);
  input rst,clk;
  input [3:0] enable;//4'b0100 clock을 멈추고 동작!
  input [11:0]keypad_in;
  output [7:0] h,m,s;

  
  wire [11:0]scan_out;
  wire valid;
  wire [3:0]r0,r1,r2,r3,r4,r5;
  wire en;
  
  keypad_scan KS(rst, clk, enable,keypad_in, scan_out, valid);
  display DP(rst, clk, enable,scan_out, valid, r0,r1,r2,r3,r4,r5, en);
  register RG1(clk, rst, r0, en, h[7:4]);
  register RG2(clk, rst, r1, en, h[3:0]);
  register RG3(clk, rst, r2, en, m[7:4]);
  register RG4(clk, rst, r3, en, m[3:0]);
  register RG5(clk, rst, r4, en, s[7:4]);
  register RG6(clk, rst, r5, en, s[3:0]);

endmodule

project/clock.v
module clock(clk,resetn,enable,set_hour,set_minute,set_second,h,m,s);
    input clk,resetn;
    input [3:0] enable;
    input [7:0] set_hour,set_minute,set_second;
    output [7:0] h,m,s;

    reg [5:0] second,minute;
    reg [4:0] hour;

    always @(posedge clk or negedge resetn) begin
        if(!resetn) begin
            second<=0;
            minute<=0;
            hour<=0;
        end
        else if(enable==4'b0100) begin//time stop and set clock
            hour<=10*set_hour[7:4]+set_hour[3:0];
            minute<=10*set_minute[7:4]+set_minute[3:0];
            second<=10*set_second[7:4]+set_second[3:0];
        end
        else begin
            second<=second+1;
            if(second==60) begin
                second<=0;
                minute<=minute+1;
                if(minute==60) begin
                    minute<=0;
                    hour<=hour+1;
                    if(hour==24) begin
                        hour<=0;
                    end
                end
            end
        end
    end

    assign h[7:4]=hour/10;
    assign h[3:0]=hour%10;
    assign m[7:4]=minute/10;
    assign m[3:0]=minute%10;
    assign s[7:4]=second/10;
    assign s[3:0]=second%10;

endmodule

project/clock_divide.v
module clock_divide(clk,resetn,clk_divided);
    input clk,resetn;
    output reg clk_divided;

    integer count;

    always @(negedge resetn or posedge clk)
    begin
        if(!resetn) begin
            count<=0;
            clk_divided<=0;
        end
    else begin
        count=count+1;
        if(count>=500) begin
            count<=0; clk_divided<=~clk_divided;
        end
    end
end

endmodule

project/keypadclock_decoder.v
module keypadclock_decoder(clk,resetn,enable,keypad_clock,setclock_clock,stopwatch_clock,alarm_clock);
    input clk,resetn;
    input [3:0] enable;
    input [23:0] keypad_clock;
    output reg [23:0] setclock_clock,stopwatch_clock,alarm_clock;

    always @(posedge clk or negedge resetn) begin
        if(!resetn)begin
            setclock_clock<=24'b0;
            stopwatch_clock<=24'bx;
            alarm_clock<=24'bx;
        end
        case(enable)
            4'b0100:setclock_clock<=keypad_clock;
            4'b0010:stopwatch_clock<=keypad_clock;
            4'b0001:alarm_clock<=keypad_clock;
        endcase
    end
endmodule

project/main.v
module main(clk,resetn,enable,keypad_in,LCD_E,LCD_RS,LCD_RW,LCD_DATA);
    input clk,resetn;
    // 4'b0000 MAIN 4'b1000 CLOCK 4'b0100 CLOCK STOP & SET CLOCK 4'b0010 STOPWATCH 4'b0001 ALARM
    input [3:0] enable;
    input [11:0]keypad_in;
    output LCD_E;
    output LCD_RS,LCD_RW;
    output [7:0] LCD_DATA;

    wire [23:0] keypad_clock,setclock_clock,stopwatch_clock,alarm_clock;
    wire [7:0] hour,minute,second;
    wire clk_divided;
    
    keypadclock_decoder kdec1(clk,resetn,enable,keypad_clock,setclock_clock,stopwatch_clock,alarm_clock);
    clock_divide cd1(clk,resetn,clk_divided);
    clock clock1(clk_divided,resetn,enable,setclock_clock[23:16],setclock_clock[15:8],setclock_clock[7:0],hour,minute,second);
    keypad kp1(resetn,clk,enable,keypad_in,keypad_clock[23:16],keypad_clock[15:8],keypad_clock[7:0]);
    textlcd lcd1(clk,resetn,enable,hour,minute,second,LCD_E,LCD_RS,LCD_RW,LCD_DATA);

endmodule

project/testbench.v
`timescale 10ms/1ps
module testbench;
    reg clk,resetn;
    reg [3:0] enable;
    reg [11:0] keypad_in;
    wire LCD_E;
    wire LCD_RS,LCD_RW;
    wire [7:0] LCD_DATA;

    main m1(clk,resetn,enable,keypad_in,LCD_E,LCD_RS,LCD_RW,LCD_DATA);

    always #5 clk=~clk;

    initial begin
        $dumpfile("clock.vcd");
        $dumpvars(-1,m1);
        clk<=0;
        resetn<=1;
        #3 resetn<=0;
        #1 resetn<=1;
        enable<=4'b0100;
        #500 keypad_in<=12'b000000000001; //1
        #100 keypad_in<=12'b0;
        #500 keypad_in<=12'b100000000000; //#
        #100 keypad_in<=12'b0;
        #500 keypad_in<=12'b010000000000; //0
        #100 keypad_in<=12'b0;
        #500 keypad_in<=12'b100000000000; //# :
        #100 keypad_in<=12'b0;
        #500 keypad_in<=12'b000000000010; //2
        #100 keypad_in<=12'b0;
        #500 keypad_in<=12'b100000000000; //#
        #100 keypad_in<=12'b0;
        #500 keypad_in<=12'b000000000100; //3
        #100 keypad_in<=12'b0;
        #500 keypad_in<=12'b100000000000; //# :
        #100 keypad_in<=12'b0;
        #500 keypad_in<=12'b000000001000; //4
        #100 keypad_in<=12'b0;
        #500 keypad_in<=12'b100000000000; //#
        #100 keypad_in<=12'b0;
        #500 keypad_in<=12'b000000010000; //5
        #100 keypad_in<=12'b0;
        #500 keypad_in<=12'b100000000000; //#
        #100 keypad_in<=12'b0;
        #500 keypad_in<=12'b001000000000; //*
        #100 keypad_in<=12'b0;
        #10000 enable<=4'b1000;
        #30000;
        $finish;
    end
endmodule

project/clock.vcd
$date
	Sun Dec 04 15:15:22 2022
$end
$version
	Icarus Verilog
$end
$timescale
	1ps
$end
$scope module testbench $end
$scope module m1 $end
$var wire 1 ! clk $end
$var wire 4 " enable [3:0] $end
$var wire 12 # keypad_in [11:0] $end
$var wire 1 $ resetn $end
$var wire 24 % stopwatch_clock [23:0] $end
$var wire 24 & setclock_clock [23:0] $end
$var wire 8 ' second [7:0] $end
$var wire 8 ( minute [7:0] $end
$var wire 24 ) keypad_clock [23:0] $end
$var wire 8 * hour [7:0] $end
$var wire 1 + clk_divided $end
$var wire 24 , alarm_clock [23:0] $end
$var wire 1 - LCD_RW $end
$var wire 1 . LCD_RS $end
$var wire 1 / LCD_E $end
$var wire 8 0 LCD_DATA [7:0] $end
$scope module cd1 $end
$var wire 1 ! clk $end
$var wire 1 $ resetn $end
$var reg 1 + clk_divided $end
$var integer 32 1 count [31:0] $end
$upscope $end
$scope module clock1 $end
$var wire 1 + clk $end
$var wire 4 2 enable [3:0] $end
$var wire 1 $ resetn $end
$var wire 8 3 set_hour [7:0] $end
$var wire 8 4 set_minute [7:0] $end
$var wire 8 5 set_second [7:0] $end
$var wire 8 6 s [7:0] $end
$var wire 8 7 m [7:0] $end
$var wire 8 8 h [7:0] $end
$var reg 5 9 hour [4:0] $end
$var reg 6 : minute [5:0] $end
$var reg 6 ; second [5:0] $end
$upscope $end
$scope module kdec1 $end
$var wire 1 ! clk $end
$var wire 4 < enable [3:0] $end
$var wire 24 = keypad_clock [23:0] $end
$var wire 1 $ resetn $end
$var reg 24 > alarm_clock [23:0] $end
$var reg 24 ? setclock_clock [23:0] $end
$var reg 24 @ stopwatch_clock [23:0] $end
$upscope $end
$scope module kp1 $end
$var wire 1 ! clk $end
$var wire 4 A enable [3:0] $end
$var wire 12 B keypad_in [11:0] $end
$var wire 1 $ rst $end
$var wire 1 C valid $end
$var wire 12 D scan_out [11:0] $end
$var wire 8 E s [7:0] $end
$var wire 4 F r5 [3:0] $end
$var wire 4 G r4 [3:0] $end
$var wire 4 H r3 [3:0] $end
$var wire 4 I r2 [3:0] $end
$var wire 4 J r1 [3:0] $end
$var wire 4 K r0 [3:0] $end
$var wire 8 L m [7:0] $end
$var wire 8 M h [7:0] $end
$var wire 1 N en $end
$scope module DP $end
$var wire 1 ! clk $end
$var wire 4 O enable [3:0] $end
$var wire 1 $ rst $end
$var wire 1 C valid $end
$var wire 12 P scan_data [11:0] $end
$var reg 1 N en $end
$var reg 4 Q r0 [3:0] $end
$var reg 4 R r1 [3:0] $end
$var reg 4 S r2 [3:0] $end
$var reg 4 T r3 [3:0] $end
$var reg 4 U r4 [3:0] $end
$var reg 4 V r5 [3:0] $end
$var reg 12 W r8 [11:0] $end
$var reg 3 X r9 [2:0] $end
$var reg 4 Y w [3:0] $end
$upscope $end
$scope module KS $end
$var wire 1 ! clk $end
$var wire 4 Z enable [3:0] $end
$var wire 12 [ keypad_in [11:0] $end
$var wire 1 $ rst $end
$var reg 1 \ en $end
$var reg 12 ] scan_out [11:0] $end
$var reg 1 C valid $end
$upscope $end
$scope module RG1 $end
$var wire 1 ! clk $end
$var wire 1 N en $end
$var wire 4 ^ in [3:0] $end
$var wire 1 $ rst $end
$var reg 4 _ out [3:0] $end
$upscope $end
$scope module RG2 $end
$var wire 1 ! clk $end
$var wire 1 N en $end
$var wire 4 ` in [3:0] $end
$var wire 1 $ rst $end
$var reg 4 a out [3:0] $end
$upscope $end
$scope module RG3 $end
$var wire 1 ! clk $end
$var wire 1 N en $end
$var wire 4 b in [3:0] $end
$var wire 1 $ rst $end
$var reg 4 c out [3:0] $end
$upscope $end
$scope module RG4 $end
$var wire 1 ! clk $end
$var wire 1 N en $end
$var wire 4 d in [3:0] $end
$var wire 1 $ rst $end
$var reg 4 e out [3:0] $end
$upscope $end
$scope module RG5 $end
$var wire 1 ! clk $end
$var wire 1 N en $end
$var wire 4 f in [3:0] $end
$var wire 1 $ rst $end
$var reg 4 g out [3:0] $end
$upscope $end
$scope module RG6 $end
$var wire 1 ! clk $end
$var wire 1 N en $end
$var wire 4 h in [3:0] $end
$var wire 1 $ rst $end
$var reg 4 i out [3:0] $end
$upscope $end
$upscope $end
$scope module lcd1 $end
$var wire 1 / LCD_E $end
$var wire 1 ! clk $end
$var wire 4 j enable [3:0] $end
$var wire 8 k hour [7:0] $end
$var wire 8 l minute [7:0] $end
$var wire 1 $ resetn $end
$var wire 8 m second [7:0] $end
$var reg 8 n LCD_DATA [7:0] $end
$var reg 1 . LCD_RS $end
$var reg 1 - LCD_RW $end
$var reg 128 o line1_data [127:0] $end
$var reg 128 p line2_data [127:0] $end
$var reg 3 q state [2:0] $end
$var integer 32 r CNT [31:0] $end
$upscope $end
$upscope $end
$upscope $end
$enddefinitions $end
#0
$dumpvars
bx r
bx q
bx p
bx o
bx n
bx m
bx l
bx k
bx j
bx i
bx h
bx g
bx f
bx e
bx d
bx c
bx b
bx a
bx `
bx _
bx ^
b0 ]
x\
bx [
bx Z
bx Y
bx X
bx W
bx V
bx U
bx T
bx S
bx R
bx Q
b0 P
bx O
0N
bx M
bx L
bx K
bx J
bx I
bx H
bx G
bx F
bx E
b0 D
0C
bx B
bx A
bx @
bx ?
bx >
bx =
bx <
bx ;
bx :
bx 9
bx 8
bx 7
bx 6
bx 5
bx 4
bx 3
bx 2
bx 1
bx 0
0/
x.
x-
bx ,
x+
bx *
bx )
bx (
bx '
bx &
bx %
1$
bx #
bx "
0!
$end
#30000000000
b0 5
b0 4
b0 3
b0 *
b0 8
b0 k
b0 (
b0 7
b0 l
b0 '
b0 6
b0 m
b0 &
b0 ?
0+
b0 1
0\
b0 F
b0 V
b0 h
b0 G
b0 U
b0 f
b0 H
b0 T
b0 d
b0 I
b0 S
b0 b
b0 J
b0 R
b0 `
b0 K
b0 Q
b0 ^
b0 Y
b0 X
b0 W
b0 _
b0 M
b0 a
b0 c
b0 L
b0 e
b0 g
b0 )
b0 =
b0 E
b0 i
b0 9
b0 :
b0 ;
b0 q
b0 r
b100000001000000010000000100000001000000010000000100000001000000010000000100000001000000010000000100000001000000010000000100000 p
b100000001000000010000000100000001000000010000000100000001000000010000000100000001000000010000000100000001000000010000000100000 o
b0 0
b0 n
1-
1.
0$
#40000000000
b100 "
b100 2
b100 <
b100 A
b100 O
b100 Z
b100 j
1$
#50000000000
b100000001000000010000000100000001000000010000000100000001000000011000000110000001110100011000000110000001110100011000000110000 p
b100000001000000010000000100000001000000010000000100000010100110100010101010100001000000100001101001100010011110100001101001011 o
b1 r
b1 1
1/
1!
#100000000000
0/
0!
#150000000000
b10 1
b10 r
1/
1!
#200000000000
0/
0!
#250000000000
b11 r
b11 1
1/
1!
#300000000000
0/
0!
#350000000000
b100 1
b100 r
1/
1!
#400000000000
0/
0!
#450000000000
b101 r
b101 1
1/
1!
#500000000000
0/
0!
#550000000000
b110 1
b110 r
1/
1!
#600000000000
0/
0!
#650000000000
b111 r
b111 1
1/
1!
#700000000000
0/
0!
#750000000000
b1000 1
b1000 r
1/
1!
#800000000000
0/
0!
#850000000000
b1001 r
b1001 1
1/
1!
#900000000000
0/
0!
#950000000000
b1010 1
b1010 r
1/
1!
#1000000000000
0/
0!
#1050000000000
b1011 r
b1011 1
1/
1!
#1100000000000
0/
0!
#1150000000000
b1100 1
b1100 r
1/
1!
#1200000000000
0/
0!
#1250000000000
b1101 r
b1101 1
1/
1!
#1300000000000
0/
0!
#1350000000000
b1110 1
b1110 r
1/
1!
#1400000000000
0/
0!
#1450000000000
b1111 r
b1111 1
1/
1!
#1500000000000
0/
0!
#1550000000000
b10000 1
b10000 r
1/
1!
#1600000000000
0/
0!
#1650000000000
b10001 r
b10001 1
1/
1!
#1700000000000
0/
0!
#1750000000000
b10010 1
b10010 r
1/
1!
#1800000000000
0/
0!
#1850000000000
b10011 r
b10011 1
1/
1!
#1900000000000
0/
0!
#1950000000000
b10100 1
b10100 r
1/
1!
#2000000000000
0/
0!
#2050000000000
b10101 r
b10101 1
1/
1!
#2100000000000
0/
0!
#2150000000000
b10110 1
b10110 r
1/
1!
#2200000000000
0/
0!
#2250000000000
b10111 r
b10111 1
1/
1!
#2300000000000
0/
0!
#2350000000000
b11000 1
b11000 r
1/
1!
#2400000000000
0/
0!
#2450000000000
b11001 r
b11001 1
1/
1!
#2500000000000
0/
0!
#2550000000000
b11010 1
b11010 r
1/
1!
#2600000000000
0/
0!
#2650000000000
b11011 r
b11011 1
1/
1!
#2700000000000
0/
0!
#2750000000000
b11100 1
b11100 r
1/
1!
#2800000000000
0/
0!
#2850000000000
b11101 r
b11101 1
1/
1!
#2900000000000
0/
0!
#2950000000000
b11110 1
b11110 r
1/
1!
#3000000000000
0/
0!
#3050000000000
b11111 r
b11111 1
1/
1!
#3100000000000
0/
0!
#3150000000000
b100000 1
b100000 r
1/
1!
#3200000000000
0/
0!
#3250000000000
b100001 r
b100001 1
1/
1!
#3300000000000
0/
0!
#3350000000000
b100010 1
b100010 r
1/
1!
#3400000000000
0/
0!
#3450000000000
b100011 r
b100011 1
1/
1!
#3500000000000
0/
0!
#3550000000000
b100100 1
b100100 r
1/
1!
#3600000000000
0/
0!
#3650000000000
b100101 r
b100101 1
1/
1!
#3700000000000
0/
0!
#3750000000000
b100110 1
b100110 r
1/
1!
#3800000000000
0/
0!
#3850000000000
b100111 r
b100111 1
1/
1!
#3900000000000
0/
0!
#3950000000000
b101000 1
b101000 r
1/
1!
#4000000000000
0/
0!
#4050000000000
b101001 r
b101001 1
1/
1!
#4100000000000
0/
0!
#4150000000000
b101010 1
b101010 r
1/
1!
#4200000000000
0/
0!
#4250000000000
b101011 r
b101011 1
1/
1!
#4300000000000
0/
0!
#4350000000000
b101100 1
b101100 r
1/
1!
#4400000000000
0/
0!
#4450000000000
b101101 r
b101101 1
1/
1!
#4500000000000
0/
0!
#4550000000000
b101110 1
b101110 r
1/
1!
#4600000000000
0/
0!
#4650000000000
b101111 r
b101111 1
1/
1!
#4700000000000
0/
0!
#4750000000000
b110000 1
b110000 r
1/
1!
#4800000000000
0/
0!
#4850000000000
b110001 r
b110001 1
1/
1!
#4900000000000
0/
0!
#4950000000000
b110010 1
b110010 r
1/
1!
#5000000000000
0/
0!
#5040000000000
b1 #
b1 B
b1 [
#5050000000000
1\
1C
b1 D
b1 P
b1 ]
b110011 r
b110011 1
1/
1!
#5100000000000
0/
0!
#5150000000000
b0 D
b0 P
b0 ]
0C
b1 Y
b1 W
b110100 1
b110100 r
1/
1!
#5200000000000
0/
0!
#5250000000000
b1 K
b1 Q
b1 ^
b110101 r
b110101 1
1/
1!
#5300000000000
0/
0!
#5350000000000
b110110 1
b110110 r
1/
1!
#5400000000000
0/
0!
#5450000000000
b110111 r
b110111 1
1/
1!
#5500000000000
0/
0!
#5550000000000
b111000 1
b111000 r
1/
1!
#5600000000000
0/
0!
#5650000000000
b111001 r
b111001 1
1/
1!
#5700000000000
0/
0!
#5750000000000
b111010 1
b111010 r
1/
1!
#5800000000000
0/
0!
#5850000000000
b111011 r
b111011 1
1/
1!
#5900000000000
0/
0!
#5950000000000
b111100 1
b111100 r
1/
1!
#6000000000000
0/
0!
#6040000000000
b0 #
b0 B
b0 [
#6050000000000
0\
b111101 r
b111101 1
1/
1!
#6100000000000
0/
0!
#6150000000000
b111110 1
b111110 r
1/
1!
#6200000000000
0/
0!
#6250000000000
b111111 r
b111111 1
1/
1!
#6300000000000
0/
0!
#6350000000000
b1000000 1
b1000000 r
1/
1!
#6400000000000
0/
0!
#6450000000000
b1000001 r
b1000001 1
1/
1!
#6500000000000
0/
0!
#6550000000000
b1000010 1
b1000010 r
1/
1!
#6600000000000
0/
0!
#6650000000000
b1000011 r
b1000011 1
1/
1!
#6700000000000
0/
0!
#6750000000000
b1000100 1
b1000100 r
1/
1!
#6800000000000
0/
0!
#6850000000000
b1000101 r
b1000101 1
1/
1!
#6900000000000
0/
0!
#6950000000000
b1000110 1
b1 q
b1000110 r
1/
1!
#7000000000000
0/
0!
#7050000000000
b111000 0
b111000 n
0-
0.
b0 r
b1000111 1
1/
1!
#7100000000000
0/
0!
#7150000000000
b1001000 1
b1 r
1/
1!
#7200000000000
0/
0!
#7250000000000
b10 r
b1001001 1
1/
1!
#7300000000000
0/
0!
#7350000000000
b1001010 1
b11 r
1/
1!
#7400000000000
0/
0!
#7450000000000
b100 r
b1001011 1
1/
1!
#7500000000000
0/
0!
#7550000000000
b1001100 1
b101 r
1/
1!
#7600000000000
0/
0!
#7650000000000
b110 r
b1001101 1
1/
1!
#7700000000000
0/
0!
#7750000000000
b1001110 1
b111 r
1/
1!
#7800000000000
0/
0!
#7850000000000
b1000 r
b1001111 1
1/
1!
#7900000000000
0/
0!
#7950000000000
b1010000 1
b1001 r
1/
1!
#8000000000000
0/
0!
#8050000000000
b1010 r
b1010001 1
1/
1!
#8100000000000
0/
0!
#8150000000000
b1010010 1
b1011 r
1/
1!
#8200000000000
0/
0!
#8250000000000
b1100 r
b1010011 1
1/
1!
#8300000000000
0/
0!
#8350000000000
b1010100 1
b1101 r
1/
1!
#8400000000000
0/
0!
